[
  {
    "id": "id1",
    "actor": "Карл Урбан",
    "character": "Уильям «Билли» Бутчер / Мясник"
  },
  {
    "id": "id2",
    "actor": "Джек Куэйд",
    "character": "Хью «Хьюи» Кэмпбелл"
  },
  {
    "id": "id3",
    "actor": "Энтони Старр",
    "character": "Джон Гиллман / Хоумлендер"
  },
  {
    "id": "id4",
    "actor": "Эрин Мориарти",
    "character": "Энни Дженьюэри / Старлайт"
  },
  {
    "id": "id5",
    "actor": "Доминик Макеллиготт",
    "character": "Мэгги Шоу / Королева Мэйв"
  }
]
